fleetio/__init__.py
fleetio/_meta.py
fleetio/config.py
fleetio/endpoint.py
fleetio/error.py
fleetio/fleetio.py
fleetio/request.py
tests/__init__.py
tests/test_endpoint.py
tests/test_fleetio.py
tests/test_request.py
pyfleetio-1.0.2.dist-info/LICENSE
pyfleetio-1.0.2.dist-info/METADATA
pyfleetio-1.0.2.dist-info/WHEEL
pyfleetio-1.0.2.dist-info/top_level.txt
pyfleetio-1.0.2.dist-info/RECORD
